doCommand(ILjava/lang/String;Ljava/lang/String;)I throws java/lang/Exception
   L0
    LINENUMBER 29 L0
    ICONST_1
    ISTORE 4
   L1
    LINENUMBER 30 L1
    ICONST_0
    ISTORE 5
   L2
    LINENUMBER 31 L2
    NEW java/io/File
    DUP
    ALOAD 3
    INVOKESPECIAL java/io/File.<init> (Ljava/lang/String;)V
    ASTORE 6
   L3
    LINENUMBER 32 L3
    ILOAD 1
    ICONST_1
    IF_ICMPNE L4
   L5
    LINENUMBER 33 L5
    GETSTATIC java/lang/System.out : Ljava/io/PrintStream;
    LDC "(%d) HELLO"
    ICONST_1
    ANEWARRAY java/lang/Object
    DUP
    ICONST_0
    ILOAD 4
    INVOKESTATIC java/lang/Integer.valueOf (I)Ljava/lang/Integer;
    AASTORE
    INVOKEVIRTUAL java/io/PrintStream.printf (Ljava/lang/String;[Ljava/lang/Object;)Ljava/io/PrintStream;
    POP
   L6
    LINENUMBER 34 L6
    IINC 5 4
    GOTO L7
   L4
    LINENUMBER 35 L4
   FRAME APPEND [I I java/io/File]
    ILOAD 1
    ICONST_2
    IF_ICMPNE L8
   L9
    LINENUMBER 36 L9
    GETSTATIC java/lang/System.out : Ljava/io/PrintStream;
    ALOAD 2
    ICONST_0
    ANEWARRAY java/lang/Object
    INVOKEVIRTUAL java/io/PrintStream.printf (Ljava/lang/String;[Ljava/lang/Object;)Ljava/io/PrintStream;
    POP
   L10
    LINENUMBER 37 L10
    ILOAD 5
    ALOAD 2
    INVOKEVIRTUAL java/lang/String.length ()I
    IADD
    ISTORE 5
    GOTO L7
   L8
    LINENUMBER 39 L8
   FRAME SAME
    ILOAD 1
    ICONST_3
    IF_ICMPNE L7
   L11
    LINENUMBER 40 L11
    GETSTATIC java/lang/System.out : Ljava/io/PrintStream;
    LDC "(%d) BYE"
    ICONST_1
    ANEWARRAY java/lang/Object
    DUP
    ICONST_0
    ILOAD 4
    INVOKESTATIC java/lang/Integer.valueOf (I)Ljava/lang/Integer;
    AASTORE
    INVOKEVIRTUAL java/io/PrintStream.printf (Ljava/lang/String;[Ljava/lang/Object;)Ljava/io/PrintStream;
    POP
   L12
    LINENUMBER 41 L12
    IINC 5 3
   L7
    LINENUMBER 43 L7
   FRAME SAME
    NEW java/io/DataOutputStream
    DUP
    NEW java/io/FileOutputStream
    DUP
    ALOAD 6
    INVOKESPECIAL java/io/FileOutputStream.<init> (Ljava/io/File;)V
    INVOKESPECIAL java/io/DataOutputStream.<init> (Ljava/io/OutputStream;)V
    ASTORE 7
   L13
    LINENUMBER 44 L13
    ALOAD 7
    LDC "Cmd %d\\%d DONE"
    ICONST_2
    ANEWARRAY java/lang/Object
    DUP
    ICONST_0
    ILOAD 4
    INVOKESTATIC java/lang/Integer.valueOf (I)Ljava/lang/Integer;
    AASTORE
    DUP
    ICONST_1
    ILOAD 5
    INVOKESTATIC java/lang/Integer.valueOf (I)Ljava/lang/Integer;
    AASTORE
    INVOKESTATIC java/lang/String.format (Ljava/lang/String;[Ljava/lang/Object;)Ljava/lang/String;
    INVOKEVIRTUAL java/io/DataOutputStream.writeUTF (Ljava/lang/String;)V
   L14
    LINENUMBER 45 L14
    ALOAD 7
    INVOKEVIRTUAL java/io/DataOutputStream.close ()V
   L15
    LINENUMBER 46 L15
    ILOAD 4
    IRETURN
